auto1111sdk/LICENSE
auto1111sdk/MANIFEST.in
auto1111sdk/__init__.py
auto1111sdk/config.json
auto1111sdk/configs/__init__.py
auto1111sdk/configs/alt-diffusion-inference.yaml
auto1111sdk/configs/alt-diffusion-m18-inference.yaml
auto1111sdk/configs/v1-inference.yaml
auto1111sdk/configs/v1-inpainting-inference.yaml
auto1111sdk/models/.DS_Store
auto1111sdk/models/VAE-approx/__init__.py
auto1111sdk/models/VAE-approx/model.pt
auto1111sdk/models/VAE-approx/vaeapprox-sdxl.pt
auto1111sdk/models/karlo/ViT-L-14_stats.th
auto1111sdk/models/karlo/__init__.py
auto1111sdk/modules/__init__.py
auto1111sdk/modules/cache.py
auto1111sdk/modules/cmd_args.py
auto1111sdk/modules/config_states.py
auto1111sdk/modules/devices.py
auto1111sdk/modules/errors.py
auto1111sdk/modules/esrgan_model_arch.py
auto1111sdk/modules/extra_networks.py
auto1111sdk/modules/extra_networks_hypernet.py
auto1111sdk/modules/face_restoration.py
auto1111sdk/modules/images.py
auto1111sdk/modules/interrogate.py
auto1111sdk/modules/lowvram.py
auto1111sdk/modules/mac_specific.py
auto1111sdk/modules/masking.py
auto1111sdk/modules/memmon.py
auto1111sdk/modules/modelloader.py
auto1111sdk/modules/options.py
auto1111sdk/modules/patches.py
auto1111sdk/modules/paths.py
auto1111sdk/modules/paths_internal.py
auto1111sdk/modules/postprocessing.py
auto1111sdk/modules/processing.py
auto1111sdk/modules/prompt_parser.py
auto1111sdk/modules/rng.py
auto1111sdk/modules/rng_philox.py
auto1111sdk/modules/safe.py
auto1111sdk/modules/script_callbacks.py
auto1111sdk/modules/script_loading.py
auto1111sdk/modules/scripts.py
auto1111sdk/modules/scripts_auto_postprocessing.py
auto1111sdk/modules/scripts_postprocessing.py
auto1111sdk/modules/sd_disable_initialization.py
auto1111sdk/modules/sd_hijack.py
auto1111sdk/modules/sd_hijack_checkpoint.py
auto1111sdk/modules/sd_hijack_clip.py
auto1111sdk/modules/sd_hijack_clip_old.py
auto1111sdk/modules/sd_hijack_open_clip.py
auto1111sdk/modules/sd_hijack_optimizations.py
auto1111sdk-0.0.95.dist-info/LICENSE
auto1111sdk-0.0.95.dist-info/METADATA
auto1111sdk-0.0.95.dist-info/WHEEL
auto1111sdk-0.0.95.dist-info/top_level.txt
auto1111sdk-0.0.95.dist-info/RECORD
