Metadata-Version: 2.1
Name: auto1111sdk
Version: 0.0.95
Summary: SDK for Automatic 1111.
Author: Auto1111 SDK
Author-email: saketh.kotamraju@gmail.com
Keywords: python,Automatic 1111,Stable Diffusion Web UI,image generation,stable diffusion,civit ai
Classifier: Development Status :: 2 - Pre-Alpha
Classifier: Intended Audience :: Developers
Classifier: Programming Language :: Python :: 3
Classifier: Operating System :: Unix
Classifier: Operating System :: MacOS :: MacOS X
Classifier: Operating System :: Microsoft :: Windows
License-File: LICENSE
Requires-Dist: GitPython ==3.1.32
Requires-Dist: Pillow ==9.5.0
Requires-Dist: accelerate ==0.21.0
Requires-Dist: basicsr ==1.4.2
Requires-Dist: blendmodes ==2022
Requires-Dist: clean-fid ==0.1.35
Requires-Dist: einops ==0.4.1
Requires-Dist: fastapi ==0.94.0
Requires-Dist: gfpgan ==1.3.8
Requires-Dist: gradio ==3.41.2
Requires-Dist: httpcore ==0.15
Requires-Dist: inflection ==0.5.1
Requires-Dist: jsonmerge ==1.8.0
Requires-Dist: kornia ==0.6.7
Requires-Dist: lark ==1.1.2
Requires-Dist: numpy ==1.23.5
Requires-Dist: omegaconf ==2.2.3
Requires-Dist: open-clip-torch ==2.20.0
Requires-Dist: piexif ==1.1.3
Requires-Dist: psutil ==5.9.5
Requires-Dist: pytorch-lightning ==1.9.4
Requires-Dist: realesrgan ==0.3.0
Requires-Dist: resize-right ==0.0.2
Requires-Dist: safetensors ==0.3.1
Requires-Dist: scikit-image ==0.21.0
Requires-Dist: timm ==0.9.2
Requires-Dist: tomesd ==0.1.3
Requires-Dist: torch ==2.1.0
Requires-Dist: torchdiffeq ==0.2.3
Requires-Dist: torchsde ==0.2.6
Requires-Dist: transformers ==4.30.2
Requires-Dist: httpx ==0.24.1
Requires-Dist: clip
